neurosymbolic/__init__.py
neurosymbolic/blocks.py
neurosymbolic/tools/bash.py
neurosymbolic/tools/python.py
neurosymbolic/types.py
neurosymbolic/z3tool.py
neurosymbolic-0.2.0.dist-info/METADATA
neurosymbolic-0.2.0.dist-info/WHEEL
neurosymbolic-0.2.0.dist-info/entry_points.txt
neurosymbolic-0.2.0.dist-info/RECORD
