Metadata-Version: 2.3
Name: neurosymbolic
Version: 0.2.0
Summary: 
Author: Thanassis Avgerinos
Author-email: thanassis.avgerinos@gmail.com
Requires-Python: >=3.11,<4.0
Classifier: Programming Language :: Python :: 3
Classifier: Programming Language :: Python :: 3.11
Classifier: Programming Language :: Python :: 3.12
Classifier: Programming Language :: Python :: 3.13
Requires-Dist: ipython (>=9.3.0,<10.0.0)
Requires-Dist: langchain-community (>=0.3.3,<0.4.0)
Requires-Dist: langchain-openai (>=0.2.3,<0.3.0)
Requires-Dist: langgraph (>=0.2.39,<0.3.0)
